example_python_package/__init__.py
example_python_package/core.py
example_python_package_billingsley-0.0.3.dist-info/LICENSE
example_python_package_billingsley-0.0.3.dist-info/METADATA
example_python_package_billingsley-0.0.3.dist-info/WHEEL
example_python_package_billingsley-0.0.3.dist-info/top_level.txt
example_python_package_billingsley-0.0.3.dist-info/RECORD
