Metadata-Version: 2.1
Name: example-python-package-billingsley
Version: 0.0.3
Summary: Example python package
Home-page: https://github.com/billingsley-john/example_python_package
Author: billingsley-john-testing
Author-email: jhnbllngsly@gmail.com
License: UNKNOWN
Platform: UNKNOWN
